{
  "title": "2016 Yearly Meeting",
  "pageId": 544,
  "namespace": 0,
  "liveUrl": "https://www.bloominglabs.org/2016_Yearly_Meeting",
  "archivedAt": "2026-04-23T07:28:04.701Z",
  "revision": {
    "id": 2574,
    "timestamp": "2016-02-01T19:45:19Z",
    "contentModel": "wikitext",
    "contentFormat": "text/x-wiki",
    "content": "January 23, 2016. 5:00PM to 9:00PM\n\n(If this is a little tl;dr, you can always skim it for the \"Action Items\" sections to know what it is we are expecting people to help with)\n\nAttendees: \n\n*Note taker: Stephen Charlesworth, Secretary (if you have more notes to add, please do! Or if you have a question about something I've recorded, please ask!)\n*Tim Buckner\n*Heath Roush - At Large Board Member\n*Ethan Broadnax\t\n*Nalette Broadnax\n*James ‘Apple’ Muncy\n*Daniel Halsey - At Large Board Member\n*Nathan Heald - President\n*Max Miller\n*Joey Cieslik\n*Kyle Dirrim\n*Eric Ost\n*Nick ‘Makevenstra’ Venstra\n*Will ‘Robot’ Wright\n*Jenett Tillotson - Treasurer\n*Allyn ‘Smokey’ Lambert\n*Murat Ozturk\n*Adam Nuwer\n*Steve Backs\n*Ian Pottmeyer\n*Neal Barrett\n*Ken Hay\n*Ryder Timberlake\n\n= Meeting notes =\n\n==Pizza And Donuts==\nThey were delicious.\nAnchovies were a surprise favorite receiving votes for 2 pizzas.\n\n== Financial information ==\nPresented by Jenett Tillotson, Treasurer.\n\nJenett and dosman moved everything to Quickbooks.\n\nA key motivation behind the move to (pay for) Quickbooks: SimpleInvoices (free open source system we were using) has reached its limit and has not been sufficient for our current needs.\n\n*We have >3mo of expenses in our bank account now (a financial goal for the year - met).\n*Makevention made some money.\n*Workshops made $1060\n*May switch from Paypal to Quickbooks for payment and donation processing (lower fee).\n\ndosman: yes it’s a fee, but there’s value in the work reduced via use of Paypal.\n\nMembership dues collected per month: $1660\n\nDetails are in the Financial Report (TODO - link to this).\n\nA question came up: how much per month should we put in savings? $200 was the agreed upon amount.\n\nSo far we have been unable to get a credit card because of strange ambiguity around our address (mailing != physical).\n\n===Taxes===\nWho files taxes? Jenett.\n\nFor us, the ‘Postcard 990’ is filed (can do this if under $50,000 revenue - otherwise have to do full 990). \n\nState of IN: no taxes for nonprofits in IN.\n\n===Hardware donations===\n*The Sunverge donation was a big one (AG 150s)!\n*They need power supplies\nIf you want one:\n*mail Jenett (jenett@bloominglabs.org)\n*let us know what you do with it!\n*don’t let it sit around - bring it back if you end up not having time to use it!\n\n===Insurance===\n*We have Public liability insurance\n*But note: members can’t sue us\n*We have Farmer’s insurance\n\n=== Donations ===\n*Let officers know you made Donation\n*If over $250, you must have a receipt (for deductions). Officers can set you up w/ a receipt.\n*See the clipboard by the donation box. Receipts are there for reference.\n*If the donation is over $500 - there’s an additional form required (TODO - need details)\n\nQuestion: What to do about unwanted donations?\n\nWe have ‘Purgatory’ area, up front in the Electronics area adjacent to the Laser Room - if items there sit there, they are recycled. Put dubious items on there.\n\nSmokey points out - for CRTs etc, you will be charged $20 but they give you a $20 Best Buy gift cert.\n\n=== Action Items ===\n*Should make a point of thanking Michelle from Envisage for her donation (who?)\n\n== Makevention 2016 Is Coming in 2016 ==\nDate:Aug 26\n\nCall for exhibitors soon.\n\nCo-hosting with MCPL.\n\nStaff Needs:\n\n*Bloominglabs booth organizer (Heath the past 2 years) - can be more than 1 person\n*‘Volunteer wrangler’\n*Somebody to help get the exhibitors up and running\nIn general: put out those flyers and cards.\n\n==Workshops and Collaborations==\n===Workshops in 2015===\n31 Workshops!\n\n37 Events!\n\n===Library collaborations and events===\nWe did several workshops, and hosted monthly ‘Arduino Club’ and ‘Python Club’ meetings, which fused together into ‘Hack Nights’.\n\nSteve Backs is a member who works for MCPL. He commented:\n\n*10-14 is any especially good target age group for these events\n*Summer is a peak time\n*Hack nights have lower attendance but we are getting some regulars\n*We are going to move Hack nights to 6pm.\n\n===If you’d like to host a workshop===\n*We have resources for PR (see the Wiki).\n*It seems to work especially well if we do workshops in clusters (for promotion, momentum, etc).\n*If you want to do one, get it on the calendar as soon as you can (deadline helps motivate you).\n\n== Membership ==\nWe have hit an ‘equilibrium’ of about 45 members.\n\nQuestion: Should we cap membership?\n\nProbably up to 50 or so is good.\n\nAgreed: No caps, but currently no need for aggressive membership drives.\n\n===Ex-Member Feedback===\nDiscussion of exit surveys.\n\nA point of constructive criticism was the messiness and disarray in some areas.\n\nSee somebody leaving a mess? Talk to them.\n\nSame story if unsafe behavior is observed.\n\n===New Member Feedback===\n\nNalette: Sometimes for new members it’s hard to find info, for example, what’s the exit protocol?\n\nMight be good to increase signage about rules.\n\nRyder T: Idea for new member orientation. Nalette B concurs this is a good idea.\n\nKyle D: Had a new member orientation package idea.\n\nSuggestion: do a New Member survey.\n\nSmokey: yes, let’s check in with them a month in.\n\nKen Hay: query about Shapeoko - what is current status, who to ask about it?\n\nCan we put the info out there about areas where help might be needed?\n\nHaving a dedicated area for certain tools would be good (like we have for the 3D printer).\n\nNick V volunteers to make that for the Shapeoko.\n\nJoey C: Sometimes it’s not as clear who does what or who to ask about what.\n\nMaybe we have nametags with our special area?\n\nKen Hay: Maybe label areas, who do I ask about this?\n\nWill Robot takes this on!\n\nRyder will help him out.\n\nIan P: How do we find out if the space has a tool?\n\nJoey C: if you would really like to familiarize yourself with items at the space, helping out with asset tagging is a great way to do that.\n\nShould we have an ‘inventory day’? No real decision or set date was made.\n\nRyder volunteers to set up a web front end for inventory stuff and querying.\n\nDaniel H: BTW Bloominglabs has a github org.\n\nIf you want a wiki account send email to contact@bloominglabs.org\n\nRyder: the culture is solid!\n\n=== Action Items ===\n* Jenett to put together ‘Expectations’ list and sign(s)\n* Ryder to  set up a web front end for inventory stuff and querying\n* Will and Ryder to label areas\n* Nick to create a dedicated space for the Shapeoko\n* Set a date for ‘Inventory day’ (who?)\n* Create a ‘new member packet’ (who?)\n* Create a ‘new member orientation’ (who?)\n* Steve to create a ‘new member survey’, follow up with members after their first month.\n\n== Low Points ==\n===The lift controversy===\nMinority objected but we are a consensus organization.\n\nAchieving consensus was quite challenging.\n\nDo we carry on w/ the consensus approach?\n\nFor now, yes.\n\n====What needs to happen for the lift====\n\nMoney - we have some left from earlier build out.\n\nNick V is leading this effort\n\nChris Dadds has the tools.\n\n====Action Items====\n*Nick to coordinate and implement lift installation.\n\n==Officer Elections==\nDoes anyone want to be an Officer?\n\nPresent officers are willing to serve another year\n\nIf you are interested: contact@bloominglabs.org: some mentoring could happen.\n\nIs everybody up every year? Currently no.\n\nPerks:\n*Fun meetings at Bw3!\n*Can put it on your resume\n*Can see the inner workings of the organization.\n*But: you have no additional power.\n\nJoey points out we should really give more lead time to put the call out to people interested in running. We did do better than last year, when we asked if anybody was interested in running AT the meeting, though.\n\nThe idea was raised (can't recall by who, exactly - sorry) that people interested in becoming Board Members could be mentored by current members.\n\nVote: Everybody’s back in (all current officers will retain their positions).\n* Nathan Heald - President\n* Jenett Tillotson - Treasurer\n* Steve Charlesworth - Secretary\n* Heath Roush - At Large\n* Daniel Halsey - At Large\n\n==The Ongoing Cleaning/Organizing Topic==\n\nOrganization efforts have helped, but the dremels are in disarray.\n\nSame story w/ the small tools in general.\n\nAdam N. suggests a sign out log for tools.\n\nKyle D: there’s a page on the Wiki if you have tools not at the space that you’d like to make available to others.\n\nIn winter leave the door to the workshop open.\n\nIn summer, leave it closed.\n\nJenett: let’s add this to expectations.\n\nAgain, let’s put a sign on the door - use Daniel H.’s sign format preferably.\n\nMax: We need quality chairs.\n\nSteve gripes about stuff on the welcome desk.\n\ndosman/Steve/Will: to move stuff from shelves up front to the back ‘boneyard’\n\nThe ‘non member storage’ area in the back is the boneyard.\n\nNobody wants to intermix member storage and boneyard - you gotta keep ‘em separated.\n\nPeople enjoy the member storage (helpful hint: get a plastic tote to protect from dust).\n\nWill’s idea: color coding: match areas to tool.\n\nDaniel has paint left over toward the cause.\n\nDon’t leave your bikes around. If they are projects, that’s OK. After about a year or so your project may be absorbed!\n\nWe should contact Christian McKay about some of his stuff. Space is at a premium in the space.\n\nNathan dealing with the octagon tables.\n\nGeneral note - sometimes visitors on public nights will leave a mess when they leave. Be on the lookout and gently encourage them to clean up.\n\n===Action Items===\n*Adam N. to create a sign out log for tools.\n*Steve, Nathan and Will will move stuff from the shelves up front to the ‘boneyard’ to make space for an ‘intake’ area.\n*Will to go ahead with his idea to color code areas and tools.\n*Nathan to deal with the octagon tables\n*(who?) to contact Christian about his stuff?\n\n==Topic: Vaping at the space==\n\nWill raised this as an issue.\n\nDo we have or need an official policy?\n\nNeal B.: no, we do not want a solid rule here.\n\nJenett: this falls under ‘be excellent to each other’.\n\nIn general, approach the person about this kind of thing.\n\nNeal B. mentioned as a city building we fall under city rules.\n\nNalette prefers a policy.\n\nTakeaway point - people have pretty strong objections to vaping at the space so take that into consideration.\n\n===Action Items===\n*Jenett to add this to the aforementioned Expectation List.\n*Nathan to send something out to the member list to remind people to ask if others mind before vaping it up.\n\n==Recognition of Member Contributions==\n*Setting up the Water heater: Apple.\n*Drywall: Joey, Jimmy, Apple.\n*Workshop lighting: Apple.\n*Joey C updated our hackerspaces.org info.\n*Thanks to anybody who did cool stuff for the space this year.\n\n==Kitchen Area==\nAre we cool going forward with a kitchen area?\n\nWe would need some cleanliness measures in place.\n\nThere’s much concern as to the cleanliness issue.\n\n==Ham Radio Area==\n\nPeople love the police scanner!\n\nNathan considering offering a radio class. There is interest.\n\nAlso: we could do a Ham Cram day.\n\nGeneral consensus: keep it, we like it!\n\nHarpo etc.’s Mesh Network: Currently nodes are Blabs and Harpo’s place.\n\n== The Dust Collector ==\nThe plan:\n*we will save $200/mo towards this.\n*Allyn will design.\n*Steve: mention on Twitter/Facebook, perhaps people would make a donation towards it.\n\nSuggestion: should we make one?\n\ndosman: we have kicked that around for a year. We have to get serious and move on it.\n\nAdam: Mainly these are for air quality while working - you still have to clean up.\n\nThey are LOUD (generally installed outside - can we? Seems it’s possible).\n\nAlso can put in a ‘quiet box’.\n\n=== Action Items ===\n* Allyn to design the system\n* Treasurer to set aside $200/mo toward the cause\n* Steve to get the word out\n* (Somebody should research/present options - who?)\n* Is there a lead on this? If not, let's find one.\n\n== Grants ==\nShould we pursue grants?\n\ndosman: An issue with these is there is a lot of oversight required, but we are a pretty free-wheeling laissez faire operation.\n\nJenett: We have experienced Grant writers among us:\n*Dan\n*Ken\n*Jenett\n*Nalette\n\nDan: NSF has community development grants\n\nNo real conclusion or plan here!\n\n== Consumables ==\nNeal: The cost of welding. How to put a price on it. Money box? $1/min? $x/inch? Some set dealy? Some open ended dealy?\n\nUp to now this has cost $20 every couple weeks. How to support this?\n\nJenett: We tend to buy our own consumables.\n\nDan suggests consumables store at Blabs (laser, 3d, welder).He is going to get rolling with this idea.\n\nAdam: Make it (welding)  $1/min. Revisit later if it makes sense.\n\nWhat costs are associated with the 3d printer? 1kg/$15.\n\nSteve: we should put a lot of this stuff in the new member packet.\n\nFor now: we’ll get one more moneybox, but everything else, pay it thru Square.\n\n=== Action Items ===\n*Get another money box (who?)\n*Dan - implement the Bloominglabs consumables store\n\n== Miscellaneous Topics ==\n===Security camera===\nAvailable online - does not record.\n\nWould be good to have some outside (we have new neighbors, not nec. malicious but they do mill around outside when shows are happening).\n\nIdea of setting up ZoneMinder floated.\n\n===Our Neighbors/Neighborhood===\n\nAllyn: What’s up w/ the parking lot situation?\n\nThe Tiny House: people are cool with it.\n\nThe bus with woodburning stove: Jenett will talk to Adam N.\n\nThe Ford Explorer that’s abandoned and has sat in the parking lot a very long time: Clemens owns that.\n\n==== Action Items ====\n*Jenett to talk to Adam N. about the bus\n\n=== Biohacking Area ===\n\nJoseph mentions there is interest in putting in a biohacking lab area. \n\nNo, not the kitchen!\n\nCurrently we have an incubator.\n\nLooking at auctions for fume hoods.\n\nThe old laser room is agreed on as best spot.\n\n=== Digital Underground (Not the ‘Humpty Dance’ Digital Underground) ===\nEric: we can do stuff via existing infrastructure (broadband), the Digital Underground runs nearby.\n\n=== Switchyard Park ===\nLikely this project will take place in steps over a long period. We are likely going to be in the current space for a while.\n\nHamilton appears receptive to having Bloominglabs stay here (has mentioned us to people, we are on his radar as a Bloomington institution).\n\nMEETING ADJOURNED\n\n\n[[Category: Meetings]]\n[[Category:Operations]]"
  }
}